genevector/__init__.py
genevector/data.py
genevector/embedding.py
genevector/model.py
genevector_nceglia-0.0.1.dist-info/LICENSE
genevector_nceglia-0.0.1.dist-info/METADATA
genevector_nceglia-0.0.1.dist-info/WHEEL
genevector_nceglia-0.0.1.dist-info/top_level.txt
genevector_nceglia-0.0.1.dist-info/RECORD
