Metadata-Version: 2.1
Name: genevector-nceglia
Version: 0.0.1
Summary: Single Cell GeneVector Library
Author-email: Nicholas Ceglia <nickceglia@gmail.com>
Project-URL: Homepage, https://github.com/nceglia/genevector
Classifier: Programming Language :: Python :: 3
Classifier: License :: OSI Approved :: MIT License
Classifier: Operating System :: OS Independent
Requires-Python: >=3.7
License-File: LICENSE
Requires-Dist: scipy
Requires-Dist: leidenalg
Requires-Dist: fast-histogram
Requires-Dist: numpy
Requires-Dist: sklearn
Requires-Dist: pandas
Requires-Dist: scanpy
Requires-Dist: umap-learn
Requires-Dist: tqdm
Requires-Dist: seaborn
Requires-Dist: matplotlib
Requires-Dist: scikit-misc (==0.1.4)
